CHANGES.md
LICENSE
MANIFEST.in
NOTICE
README.rst
do_benchmark.py
do_tests.py
setup.py
PyRATA.egg-info/PKG-INFO
PyRATA.egg-info/SOURCES.txt
PyRATA.egg-info/dependency_links.txt
PyRATA.egg-info/requires.txt
PyRATA.egg-info/top_level.txt
docs/user-guide.rst
more/code-optimize.sh
more/code-restore.sh
more/measure_pattern_time_v1.py
pyrata/__init__.py
pyrata/compiled_pattern.py
pyrata/lexer.py
pyrata/match.py
pyrata/nfa.py
pyrata/nltk.py
pyrata/parsetab.py
pyrata/re.py
pyrata/state.py
pyrata/syntactic_step_parser.py