Metadata-Version: 1.0
Name: PyRATA
Version: 0.4.1
Summary: Python Rule-based feAture sTructure Analysis
Home-page: https://github.com/nicolashernandez/PyRATA
Author: Nicolas Hernandez
Author-email: nicolas.hernandez@gmail.com
License: Apache 2.0
Keywords: NLP rule-based text mining machine learning natural language processing
Platform: UNKNOWN
